{
  "record": 1017,
  "cid": 20849296,
  "name": "polyethyleneglycol tridecyl ether phosphate",
  "CAS": "9046-01-9",
  "EC": "618-558-4",
  "FCM": 578,
  "Ref": "79600",
  "Additive_or_PPA": true,
  "Use_as_monomer_macromolecule": false,
  "FRFapplicable": false,
  "SML": 5.0,
  "SMLunit": "mg/kg",
  "SMLTrestrictions": "",
  "SMLTGroupFCMsubstances": null,
  "SMLT": 5.0,
  "SMLTunit": "mg/kg",
  "Restrictions": "For materials and articles intended for contact with aqueous foods only.Polyethyleneglycol (EO ≤ 11) tridecyl ether phosphate (mono-and dialkyl ester) with a maximum 10 % content of polyethyleneglycol (EO ≤ 11) tridecylether.",
  "NotesCompliance": "",
  "Notes": "",
  "Physicalform": "",
  "ExpressedAs": "",
  "engine": "SFPPy: EUFCMannex1.py",
  "csvFile": "fcm-and-articles-regulation--annex-i---authorised-substances-export.csv",
  "date": "2025-03-13 09:25:38"
}