{
  "record": 1046,
  "cid": null,
  "name": "resin acids and rosin acids",
  "CAS": "73138-82-6",
  "EC": "277-299-1",
  "FCM": 741,
  "Ref": "8361024070",
  "Additive_or_PPA": true,
  "Use_as_monomer_macromolecule": true,
  "FRFapplicable": false,
  "SML": 60.0,
  "SMLunit": "mg/kg",
  "SMLTrestrictions": "",
  "SMLTGroupFCMsubstances": null,
  "SMLT": 60.0,
  "SMLTunit": "mg/kg",
  "Restrictions": "",
  "NotesCompliance": "",
  "Notes": "",
  "Physicalform": "",
  "ExpressedAs": "",
  "engine": "SFPPy: EUFCMannex1.py",
  "csvFile": "fcm-and-articles-regulation--annex-i---authorised-substances-export.csv",
  "date": "2025-03-13 09:25:38"
}