{
  "record": 681,
  "cid": 15088,
  "name": "isophthalic acid, dimethyl ester",
  "CAS": "1459-93-4",
  "EC": "215-951-9",
  "FCM": 420,
  "Ref": "19210",
  "Additive_or_PPA": false,
  "Use_as_monomer_macromolecule": true,
  "FRFapplicable": false,
  "SML": 0.05,
  "SMLunit": "mg/kg",
  "SMLTrestrictions": "",
  "SMLTGroupFCMsubstances": null,
  "SMLT": 0.05,
  "SMLTunit": "mg/kg",
  "Restrictions": "",
  "NotesCompliance": "",
  "Notes": "",
  "Physicalform": "",
  "ExpressedAs": "",
  "engine": "SFPPy: EUFCMannex1.py",
  "csvFile": "fcm-and-articles-regulation--annex-i---authorised-substances-export.csv",
  "date": "2025-03-13 09:25:38"
}