{
  "record": 160,
  "cid": 39800,
  "name": "2-methyl-4-isothiazolin-3-one",
  "CAS": "2682-20-4",
  "EC": "220-239-6",
  "FCM": 451,
  "Ref": "66755",
  "Additive_or_PPA": true,
  "Use_as_monomer_macromolecule": false,
  "FRFapplicable": false,
  "SML": 0.5,
  "SMLunit": "mg/kg",
  "SMLTrestrictions": "",
  "SMLTGroupFCMsubstances": null,
  "SMLT": 0.5,
  "SMLTunit": "mg/kg",
  "Restrictions": "Only to be used in aqueous polymer dispersions and emulsions.",
  "NotesCompliance": "",
  "Notes": "",
  "Physicalform": "",
  "ExpressedAs": "",
  "engine": "SFPPy: EUFCMannex1.py",
  "csvFile": "fcm-and-articles-regulation--annex-i---authorised-substances-export.csv",
  "date": "2025-03-13 09:25:38"
}