{
  "record": 454,
  "cid": 3601357,
  "name": "bis(2,6-di-tert-butyl-4-methylphenyl)pentaerythritol diphosphite",
  "CAS": "80693-00-1",
  "EC": "410-290-4",
  "FCM": 746,
  "Ref": "38810",
  "Additive_or_PPA": true,
  "Use_as_monomer_macromolecule": false,
  "FRFapplicable": true,
  "SML": 5.0,
  "SMLunit": "mg/kg",
  "SMLTrestrictions": "",
  "SMLTGroupFCMsubstances": null,
  "SMLT": 5.0,
  "SMLTunit": "mg/kg",
  "Restrictions": "SML expressed as sum of phosphite and phosphate.",
  "NotesCompliance": "",
  "Notes": "",
  "Physicalform": "",
  "ExpressedAs": "As sum of phosphite and phosphate",
  "engine": "SFPPy: EUFCMannex1.py",
  "csvFile": "fcm-and-articles-regulation--annex-i---authorised-substances-export.csv",
  "date": "2025-03-13 09:25:38"
}