{
  "FCA": "0541",
  "cid": null,
  "CAS": "32555-39-8",
  "authorized in": [
    "paper and board"
  ],
  "ChineseName": "N ,N-二甲基 -N-2-丙烯基 -2-丙烯基 -1-铵氯化物与乙二醛和 2-丙烯酰胺的聚合物",
  "engine": "SFPPy: GBappendixA module",
  "csfile": "GB9685-2016.csv",
  "date": "2025-04-02 07:48:09",
  "paper and board": {
    "materials": [
      "0.24"
    ],
    "CP0max": null,
    "QMSMLraw": "ND(丙烯酰胺 :SML,DL=0.01mg/kg);1.5mg/dm2(乙二醛:QM)",
    "SML": null,
    "QM": 2.0,
    "DL": 0.01,
    "SMLT": null,
    "SMLTraw": "黏度小于",
    "SMLTcomment": "100cps(1#60rpm)",
    "comment1": "",
    "comment2": "",
    "table_id": "paper and board"
  }
}