{
  "FCA": "0180",
  "cid": 13698,
  "CAS": "948-65-2",
  "authorized in": [
    "plastics"
  ],
  "ChineseName": "2-苯基 -1H-吲哚",
  "engine": "SFPPy: GBappendixA module",
  "csfile": "GB9685-2016.csv",
  "date": "2025-04-02 07:48:09",
  "plastics": {
    "materials": [
      "PP",
      "PE",
      "PS",
      "PVC",
      "PA",
      "PC",
      "ABS",
      "AS",
      "PET"
    ],
    "CP0max": null,
    "QMSMLraw": "15(SML)",
    "SML": 15.0,
    "QM": null,
    "DL": null,
    "SMLT": null,
    "SMLTraw": "",
    "SMLTcomment": "",
    "comment1": "",
    "comment2": "",
    "table_id": "plastics"
  }
}