{
  "FCA": "0816",
  "cid": 7773,
  "CAS": "105-74-8",
  "authorized in": [
    "plastics",
    "adhesives"
  ],
  "ChineseName": "过氧化月桂酰",
  "engine": "SFPPy: GBappendixA module",
  "csfile": "GB9685-2016.csv",
  "date": "2025-04-02 07:48:09",
  "plastics": {
    "materials": [
      "PP",
      "PE",
      "PS"
    ],
    "CP0max": 2000.0,
    "QMSMLraw": "",
    "SML": null,
    "QM": null,
    "DL": null,
    "SMLT": null,
    "SMLTraw": "",
    "SMLTcomment": "",
    "comment1": "",
    "comment2": "",
    "table_id": "plastics"
  },
  "adhesives": {
    "materials": [
      "按生产需要适量使用"
    ],
    "CP0max": null,
    "QMSMLraw": "",
    "SML": null,
    "QM": null,
    "DL": null,
    "SMLT": null,
    "SMLTraw": "",
    "SMLTcomment": "",
    "comment1": "",
    "comment2": "",
    "table_id": "adhesives"
  }
}