{
  "FCA": "0555",
  "cid": 23671849,
  "CAS": "25383-99-7",
  "authorized in": [
    "paper and board"
  ],
  "ChineseName": "O-十八烷酰乳酸钠",
  "engine": "SFPPy: GBappendixA module",
  "csfile": "GB9685-2016.csv",
  "date": "2025-04-02 07:48:09",
  "paper and board": {
    "materials": [
      "0.02"
    ],
    "CP0max": null,
    "QMSMLraw": "",
    "SML": null,
    "QM": null,
    "DL": null,
    "SMLT": null,
    "SMLTraw": "",
    "SMLTcomment": "",
    "comment1": "",
    "comment2": "",
    "table_id": "paper and board"
  }
}