{
  "FCA": "1143",
  "cid": 161663,
  "CAS": "30381-98-7",
  "authorized in": [
    "paper and board"
  ],
  "ChineseName": "双 [乙基 (全氟辛烷 )磺酰胺乙基 ]磷酸铵",
  "engine": "SFPPy: GBappendixA module",
  "csfile": "GB9685-2016.csv",
  "date": "2025-04-02 07:48:09",
  "paper and board": {
    "materials": [
      "0.5(以干纸计 )"
    ],
    "CP0max": null,
    "QMSMLraw": "",
    "SML": null,
    "QM": null,
    "DL": null,
    "SMLT": null,
    "SMLTraw": "",
    "SMLTcomment": "",
    "comment1": "",
    "comment2": "",
    "table_id": "paper and board"
  }
}