{
  "record": 1069,
  "cid": null,
  "name": "2-Propenoic acid, 2-methyl-, methyl ester, polymer with 1,3-butadiene, diethenylbenzene, ethenylbenzene and ethyl 2-propenoate",
  "CAS": "59858-50-3",
  "FCNNo": "1499",
  "FoodContactSubstance": "2-Propenoic acid, 2-methyl-, methyl ester, polymer with 1,3-butadiene, diethenylbenzene, ethenylbenzene and ethyl 2-propenoate (CAS Reg. No. 59858-50-3).",
  "mixture": false,
  "FCSreplacedby": "",
  "FCSreplacedby_record": null,
  "notifier": "The Dow Chemical Company",
  "manufacturer": "The Dow Chemical Company",
  "NotificationDate": "04/02/2015",
  "engine": "SFPPy: USFDAfcn.py",
  "csfile": "FCN.csv",
  "date": "2025-03-31 10:25:03"
}