{
  "record": 1479,
  "cid": null,
  "name": "Fatty acids, C18-unsaturated, dimers, hydrogenated, polymers with caprolactam and hexamethylenediamine",
  "CAS": "",
  "FCNNo": "2064",
  "FoodContactSubstance": "Fatty acids, C18-unsaturated, dimers, hydrogenated, polymers with caprolactam and hexamethylenediamine (CAS Reg. No.475994-94-6).",
  "mixture": false,
  "FCSreplacedby": "",
  "FCSreplacedby_record": null,
  "notifier": "Nylon Corporation of America, Inc. (NYCOA)",
  "manufacturer": "Nylon Corporation of America, Inc. (NYCOA)",
  "NotificationDate": "08/19/2020",
  "engine": "SFPPy: USFDAfcn.py",
  "csfile": "FCN.csv",
  "date": "2025-03-31 10:25:03"
}