{
  "record": 1412,
  "cid": 26041,
  "name": "Zinc pyrithione",
  "CAS": "13463-41-7",
  "FCNNo": "2139",
  "FoodContactSubstance": "Zinc pyrithione (CAS Reg. No. 13463-41-7) <strong>REPLACES FCN 2031</strong>",
  "mixture": false,
  "FCSreplacedby": "",
  "FCSreplacedby_record": null,
  "notifier": "Symphony Environmental Technologies Plc",
  "manufacturer": "Symphony Environmental Technologies Plc",
  "NotificationDate": "07/13/2021",
  "engine": "SFPPy: USFDAfcn.py",
  "csfile": "FCN.csv",
  "date": "2025-03-31 10:25:03"
}