{
  "record": 1366,
  "cid": 91290213,
  "name": "Trimethylolpropane trisorbate (TMPTS)",
  "CAS": "2307636-51-5",
  "FCNNo": "2005",
  "FoodContactSubstance": "Trimethylolpropane trisorbate (TMPTS) (CAS Reg. No. 2307636-51-5).",
  "mixture": false,
  "FCSreplacedby": "",
  "FCSreplacedby_record": null,
  "notifier": "Milliken Chemical",
  "manufacturer": "Milliken Chemical",
  "NotificationDate": "12/26/2019",
  "engine": "SFPPy: USFDAfcn.py",
  "csfile": "FCN.csv",
  "date": "2025-03-31 10:25:03"
}