{
  "record": 1127,
  "cid": null,
  "name": "Isotridecanol phosphite condensation product with butylidenebis(2-(1,1-dimethylethyl)-5-methyl-4,1-phenylene).",
  "CAS": "",
  "FCNNo": "1604",
  "FoodContactSubstance": "Isotridecanol phosphite condensation product with butylidenebis(2-(1,1-dimethylethyl)-5-methyl-4,1-phenylene).",
  "mixture": false,
  "FCSreplacedby": "",
  "FCSreplacedby_record": null,
  "notifier": "ADEKA Corporation",
  "manufacturer": "ADEKA Corporation",
  "NotificationDate": "01/09/2016",
  "engine": "SFPPy: USFDAfcn.py",
  "csfile": "FCN.csv",
  "date": "2025-03-31 10:25:03"
}