{
  "record": 1595,
  "cid": null,
  "name": "Poly(1,4-butylene glycol-co-succinic acid), cross-linked with malic acid. <strong>REPLACES FCN 1817</strong>",
  "CAS": "",
  "FCNNo": "2271",
  "FoodContactSubstance": "Poly(1,4-butylene glycol-co-succinic acid), cross-linked with malic acid. <strong>REPLACES FCN 1817</strong>",
  "mixture": false,
  "FCSreplacedby": "",
  "FCSreplacedby_record": null,
  "notifier": "PTT MCC Biochem Company Limited",
  "manufacturer": "PTT MCC Biochem Company Limited",
  "NotificationDate": "03/02/2023",
  "engine": "SFPPy: USFDAfcn.py",
  "csfile": "FCN.csv",
  "date": "2025-03-31 10:25:03"
}