{
  "record": 1536,
  "cid": null,
  "name": "N,N'-dioleoylethylenediamine (CAS. Reg. No. 110-31-6).",
  "CAS": "",
  "FCNNo": "2197",
  "FoodContactSubstance": "N,N'-dioleoylethylenediamine (CAS. Reg. No. 110-31-6).",
  "mixture": false,
  "FCSreplacedby": "",
  "FCSreplacedby_record": null,
  "notifier": "SK Functional Polymer S.A.S.",
  "manufacturer": "SK Functional Polymer S.A.S.",
  "NotificationDate": "02/19/2022",
  "engine": "SFPPy: USFDAfcn.py",
  "csfile": "FCN.csv",
  "date": "2025-03-31 10:25:03"
}